pydatastructs/__init__.py
pydatastructs/binarysearchtree.py
pydatastructs/heap.py
pydatastructs/linkedlist.py
pydatastructs/list.py
pydatastructs/maxheap.py
pydatastructs/minheap.py
pydatastructs/queue.py
pydatastructs/stack.py
pydatastructs/tree.py
pydatastructs-1.2.3.dist-info/LICENSE
pydatastructs-1.2.3.dist-info/METADATA
pydatastructs-1.2.3.dist-info/WHEEL
pydatastructs-1.2.3.dist-info/top_level.txt
pydatastructs-1.2.3.dist-info/RECORD
