Metadata-Version: 2.1
Name: pydatastructs
Version: 1.2.3
Summary: A package that contains common data structures
Home-page: https://github.com/yoshiohasegawa/python-data-structures
Author: Yoshio Hasegawa
Author-email: yoshio.seisuke.hasegawa@gmail.com
License: MIT
Download-URL: https://github.com/yoshiohasegawa/python-data-structures/archive/refs/tags/v1.2.3.tar.gz
Keywords: Python,Data Structures,Collections,Stack,Queue,Tree,Binary Search Tree,Heap,Linked List
Platform: UNKNOWN
Classifier: Development Status :: 4 - Beta
Classifier: Intended Audience :: Developers
Classifier: License :: OSI Approved :: MIT License
Classifier: Programming Language :: Python :: 3.9
Classifier: Topic :: Software Development
Classifier: Topic :: Software Development :: Build Tools
Classifier: Topic :: Software Development :: Libraries
Classifier: Topic :: Software Development :: Libraries :: Python Modules
Requires-Dist: typing
